{"assets":{"DC1DFFDD227C20CFB5C1E9DD9F47EA72":{"type":"texture","index":0,"url":{"native":"assets\/71EB70FC-65AF-43E8-9539-F07E94B4CA48.pdf"},"width":1024,"height":768},"627AE883ADDC33A435EA85191E614751":{"type":"texture","index":1,"url":{"native":"assets\/71EB70FC-65AF-43E8-9539-F07E94B4CA48.pdf"},"width":1024,"height":768}},"events":[{"effects":[{"beginTime":0,"baseLayer":{"animations":[],"initialState":{"affineTransform":[1,0,0,1,0,0],"masksToBounds":false,"rotation":0,"scale":1,"position":{"pointX":512,"pointY":384},"width":1024,"sublayerTransform":[1,0,0,0,0,1,0,0,0,0,1,0,0,0,0,1],"contentsRect":{"y":0,"x":0,"width":1,"height":1},"opacity":1,"edgeAntialiasingMask":251658240,"height":768,"hidden":false,"anchorPoint":{"pointX":0.5,"pointY":0.5}},"objectID":"0","layers":[{"animations":[],"initialState":{"affineTransform":[1,0,0,1,0,0],"masksToBounds":false,"rotation":0,"scale":1,"position":{"pointX":512,"pointY":384},"width":1024,"sublayerTransform":[1,0,0,0,0,1,0,0,0,0,1,-0.00049229876906403734,0,0,0,1],"contentsRect":{"y":0,"x":0,"width":1,"height":1},"opacity":1,"edgeAntialiasingMask":251658240,"height":768,"hidden":false,"anchorPoint":{"pointX":0.5,"pointY":0.5}},"layers":[{"animations":[],"layers":[],"texturedRectangle":{"isBackgroundTexture":false,"singleTextureOpacity":1,"textureType":0,"textBaseline":0,"textXHeight":0,"isVerticalText":false},"initialState":{"affineTransform":[1,0,0,1,0,0],"masksToBounds":false,"rotation":0,"scale":1,"position":{"pointX":512,"pointY":384},"width":1024,"sublayerTransform":[1,0,0,0,0,1,0,0,0,0,1,0,0,0,0,1],"contentsRect":{"y":0,"x":0,"width":1,"height":1},"opacity":1,"edgeAntialiasingMask":0,"height":768,"hidden":false,"anchorPoint":{"pointX":0.5,"pointY":0.5}},"texture":"627AE883ADDC33A435EA85191E614751"},{"animations":[{"additive":false,"timeOffset":0,"beginTime":0,"from":{"scalar":false},"repeatCount":0,"fillMode":"both","duration":0.001,"autoreverses":false,"property":"hidden","to":{"scalar":true},"removedOnCompletion":false}],"layers":[],"texturedRectangle":{"isBackgroundTexture":false,"singleTextureOpacity":1,"textureType":0,"textBaseline":0,"textXHeight":0,"isVerticalText":false},"initialState":{"affineTransform":[1,0,0,1,0,0],"masksToBounds":false,"rotation":0,"scale":1,"position":{"pointX":512,"pointY":384},"width":1024,"sublayerTransform":[1,0,0,0,0,1,0,0,0,0,1,0,0,0,0,1],"contentsRect":{"y":0,"x":0,"width":1,"height":1},"opacity":1,"edgeAntialiasingMask":0,"height":768,"hidden":false,"anchorPoint":{"pointX":0.5,"pointY":0.5}},"texture":"DC1DFFDD227C20CFB5C1E9DD9F47EA72"}]}]},"effects":[],"duration":0.001,"type":"transition","attributes":{"direction":0},"name":"none","objectID":"0"}],"automaticPlay":false,"hyperlinks":[{"url":"http:\/\/j12t.org","targetRectangle":{"y":744.50527974963188,"x":173.94736177062987,"width":40.560000000000031,"height":13.66400146484375}}],"accessibility":[{"text":"Example test: “If Alice follows Bob, does she receive his new posts?”","targetRectangle":{"y":161.45263671875,"x":79.999995040893737,"width":544.05119999999988,"height":19.596765136718744}},{"text":"Provided that …","targetRectangle":{"y":179.57704176910482,"x":114.19999485015887,"width":128.52000000000004,"height":34.63268263339998}},{"text":"@alice@a.example GETs @bob@b.example’s WebFinger file","targetRectangle":{"y":212.74577252127057,"x":146.99999405543031,"width":445.46879999999987,"height":34.649601578712463}},{"text":"@alice@a.example GETs @bob@b.example’s Actor file","targetRectangle":{"y":245.91281137850166,"x":146.99999405543031,"width":405.35040000000004,"height":34.649601578712463}},{"text":"@alice@a.example signs and POSTs a “follow” to @bob@b.example’s inbox","targetRectangle":{"y":279.07985023573275,"x":146.99999405543031,"width":565.60559999999987,"height":34.649601578712463}},{"text":"@bob@b.example GETs @alice@a.example’s WebFinger file","targetRectangle":{"y":312.24688909296384,"x":146.99999405543031,"width":445.46879999999987,"height":34.649601578712463}},{"text":"@bob@b.example GETs @alice@a.example’s Actor file","targetRectangle":{"y":345.41392795019493,"x":146.99999405543031,"width":405.35040000000004,"height":34.649601578712463}},{"text":"@bob@b.example validates @alice@a.example’s signature on the “follow”","targetRectangle":{"y":378.58096680742602,"x":146.99999405543031,"width":550.67039999999986,"height":34.649601578712463}},{"text":"@bob@b.example accepts the “follow”","targetRectangle":{"y":411.74800566465711,"x":146.99999405543031,"width":291.04320000000001,"height":34.649601578712463}},{"text":"@bob@b.example signs and POSTs an “accept” to @a@a.example’s inbox","targetRectangle":{"y":444.91504452188821,"x":146.99999405543031,"width":556.33199999999965,"height":34.649601578712463}},{"text":"@alice@a.example validates @bob@b.example’s signature on the “accept”","targetRectangle":{"y":478.0820833791193,"x":146.99999405543031,"width":557.55839999999989,"height":34.649601578712407}},{"text":"Now this action …","targetRectangle":{"y":511.24912223635039,"x":114.19999485015887,"width":146.19360000000006,"height":34.632682633399952}},{"text":"@bob@b.example “creates” a “note”","targetRectangle":{"y":544.41785298851619,"x":146.99999405543031,"width":274.89840000000004,"height":34.649601578712463}},{"text":"Leads to this desired result to be verified:","targetRectangle":{"y":577.58489184574728,"x":114.19999485015887,"width":331.32959999999991,"height":34.632682633399895}},{"text":"@alice@a.example’s inbox receives the “create note”, correctly signed by @bob@b.example’s key","targetRectangle":{"y":610.75362259791291,"x":144.19999560356143,"width":656.66160000000002,"height":31.696641373634407}},{"text":"Problem:","targetRectangle":{"y":641.21595754605596,"x":75.799999237060547,"width":67.536000000000001,"height":34.649601578712463}},{"text":"Many steps to get a.example and b.example into the state where the actual test can be performed","targetRectangle":{"y":674.38299640328705,"x":105.79999923706055,"width":735.97439999999995,"height":34.649601578712463}},{"text":"© CC-BY-NC Johannes Ernst j12t.org","targetRectangle":{"y":744.50527974963188,"x":12.331361770629883,"width":202.17600000000002,"height":13.66400146484375}},{"text":"Problem: setup of distributed state","targetRectangle":{"y":38.666667938232422,"x":59,"width":902.53800089183449,"height":68.346603393554688}}],"baseLayer":{"animations":[],"initialState":{"affineTransform":[1,0,0,1,0,0],"masksToBounds":false,"rotation":0,"scale":1,"position":{"pointX":512,"pointY":384},"width":1024,"sublayerTransform":[1,0,0,0,0,1,0,0,0,0,1,0,0,0,0,1],"contentsRect":{"y":0,"x":0,"width":1,"height":1},"opacity":1,"edgeAntialiasingMask":251658240,"height":768,"hidden":false,"anchorPoint":{"pointX":0.5,"pointY":0.5}},"objectID":"0","layers":[{"animations":[],"initialState":{"affineTransform":[1,0,0,1,0,0],"masksToBounds":false,"rotation":0,"scale":1,"position":{"pointX":512,"pointY":384},"width":1024,"sublayerTransform":[1,0,0,0,0,1,0,0,0,0,1,-0.00049229876906403734,0,0,0,1],"contentsRect":{"y":0,"x":0,"width":1,"height":1},"opacity":1,"edgeAntialiasingMask":251658240,"height":768,"hidden":false,"anchorPoint":{"pointX":0.5,"pointY":0.5}},"layers":[{"animations":[],"layers":[],"texturedRectangle":{"isBackgroundTexture":false,"singleTextureOpacity":1,"textureType":0,"textBaseline":0,"textXHeight":0,"isVerticalText":false},"initialState":{"affineTransform":[1,0,0,1,0,0],"masksToBounds":false,"rotation":0,"scale":1,"position":{"pointX":512,"pointY":384},"width":1024,"sublayerTransform":[1,0,0,0,0,1,0,0,0,0,1,0,0,0,0,1],"contentsRect":{"y":0,"x":0,"width":1,"height":1},"opacity":1,"edgeAntialiasingMask":0,"height":768,"hidden":false,"anchorPoint":{"pointX":0.5,"pointY":0.5}},"texture":"DC1DFFDD227C20CFB5C1E9DD9F47EA72"}]}]}}]}